{"assets":{"B0964F140D9B11107918EB4C67E722F6":{"type":"texture","index":1,"assetRequest":{"type":"slide","state":"contents","slide":"none"},"url":{"native":"assets\/7EF9B165-2BD6-49F6-A759-1304C57B5E29.pdf"},"width":1920,"height":1080},"E2B5DC116AB8233B0A2B9A60ACC6231B":{"type":"texture","index":0,"assetRequest":{"type":"slide","state":"contents","slide":"none"},"url":{"native":"assets\/7EF9B165-2BD6-49F6-A759-1304C57B5E29.pdf"},"width":1920,"height":1080}},"events":[{"effects":[{"beginTime":0,"baseLayer":{"animations":[],"initialState":{"affineTransform":[1,0,0,1,0,0],"masksToBounds":false,"rotation":0,"scale":1,"position":{"pointX":960,"pointY":540},"width":1920,"sublayerTransform":[1,0,0,0,0,1,0,0,0,0,1,0,0,0,0,1],"contentsRect":{"y":0,"x":0,"width":1,"height":1},"opacity":1,"edgeAntialiasingMask":251658240,"height":1080,"hidden":false,"anchorPoint":{"pointX":0.5,"pointY":0.5}},"objectID":"0","layers":[{"animations":[],"initialState":{"affineTransform":[1,0,0,1,0,0],"masksToBounds":false,"rotation":0,"scale":1,"position":{"pointX":960,"pointY":540},"width":1920,"sublayerTransform":[1,0,0,0,0,1,0,0,0,0,1,-0.00035007912466775983,0,0,0,1],"contentsRect":{"y":0,"x":0,"width":1,"height":1},"opacity":1,"edgeAntialiasingMask":251658240,"height":1080,"hidden":false,"anchorPoint":{"pointX":0.5,"pointY":0.5}},"layers":[{"animations":[],"layers":[],"texturedRectangle":{"isBackgroundTexture":false,"singleTextureOpacity":1,"textureType":0,"textBaseline":0,"textXHeight":0,"isVerticalText":false},"initialState":{"affineTransform":[1,0,0,1,0,0],"masksToBounds":false,"rotation":0,"scale":1,"position":{"pointX":960,"pointY":540},"width":1920,"sublayerTransform":[1,0,0,0,0,1,0,0,0,0,1,0,0,0,0,1],"contentsRect":{"y":0,"x":0,"width":1,"height":1},"opacity":1,"edgeAntialiasingMask":0,"height":1080,"hidden":false,"anchorPoint":{"pointX":0.5,"pointY":0.5}},"texture":"B0964F140D9B11107918EB4C67E722F6"},{"animations":[{"additive":false,"timeOffset":0,"beginTime":0,"from":{"scalar":false},"repeatCount":0,"fillMode":"both","duration":0.01,"autoreverses":false,"property":"hidden","to":{"scalar":true},"removedOnCompletion":false}],"layers":[],"texturedRectangle":{"isBackgroundTexture":false,"singleTextureOpacity":1,"textureType":0,"textBaseline":0,"textXHeight":0,"isVerticalText":false},"initialState":{"affineTransform":[1,0,0,1,0,0],"masksToBounds":false,"rotation":0,"scale":1,"position":{"pointX":960,"pointY":540},"width":1920,"sublayerTransform":[1,0,0,0,0,1,0,0,0,0,1,0,0,0,0,1],"contentsRect":{"y":0,"x":0,"width":1,"height":1},"opacity":1,"edgeAntialiasingMask":0,"height":1080,"hidden":false,"anchorPoint":{"pointX":0.5,"pointY":0.5}},"texture":"E2B5DC116AB8233B0A2B9A60ACC6231B"}]}]},"effects":[],"duration":0.01,"type":"transition","attributes":{"direction":0},"name":"none","objectID":"0"}],"automaticPlay":false,"hyperlinks":[],"accessibility":[{"text":"A classic interview question!","targetRectangle":{"y":242.76913452148438,"x":954.68349026246506,"width":565.44155196289057,"height":53}},{"text":"Write a function that takes a number to go up to","targetRectangle":{"y":290.46913325786591,"x":954.68349026246506,"width":865.28964935058593,"height":123.25999867916107}},{"text":"Then it counts up the numbers","targetRectangle":{"y":408.42913067340851,"x":954.68349026246506,"width":617.83532910644522,"height":75.559999942779541}},{"text":"It prints “Fizz” if the number divides by 3","targetRectangle":{"y":478.68912935256958,"x":954.68349026246506,"width":811.59457209960919,"height":75.559999942779541}},{"text":"It prints “Buzz” if the number divides by 5","targetRectangle":{"y":548.94912803173065,"x":954.68349026246506,"width":831.58635624023418,"height":75.559999942779541}},{"text":"It prints “FizzBuzz” if the number goes into both 3 and 5","targetRectangle":{"y":619.20912671089172,"x":954.68349026246506,"width":865.45402404785136,"height":123.25999867916107}},{"text":"It prints the number in all other cases","targetRectangle":{"y":737.16912412643433,"x":954.68349026246506,"width":748.04930438476549,"height":75.559999942779541}},{"text":"See the example from 1 - 15 on the left","targetRectangle":{"y":807.4291228055954,"x":954.68349026246506,"width":766.67797561523457,"height":75.559999942779541}},{"text":"The modulo operator % sure comes in handy here!","targetRectangle":{"y":877.68912148475647,"x":954.68349026246506,"width":756.06953194824223,"height":123.25999867916107}},{"text":"1","targetRectangle":{"y":296.63244533538818,"x":184.12210083007812,"width":21.673828125,"height":41}},{"text":"2","targetRectangle":{"y":337.63244533538818,"x":184.12210083007812,"width":21.673828125,"height":41}},{"text":"Fizz","targetRectangle":{"y":378.63244533538818,"x":184.12210083007812,"width":86.6953125,"height":41}},{"text":"4","targetRectangle":{"y":419.63244533538818,"x":184.12210083007812,"width":21.673828125,"height":41}},{"text":"Buzz","targetRectangle":{"y":460.63244533538818,"x":184.12210083007812,"width":86.6953125,"height":41}},{"text":"Fizz","targetRectangle":{"y":501.63244533538818,"x":184.12210083007812,"width":86.6953125,"height":41}},{"text":"7","targetRectangle":{"y":542.63244533538818,"x":184.12210083007812,"width":21.673828125,"height":41}},{"text":"8","targetRectangle":{"y":583.63244533538818,"x":184.12210083007812,"width":21.673828125,"height":41}},{"text":"Fizz","targetRectangle":{"y":624.63244533538818,"x":184.12210083007812,"width":86.6953125,"height":41}},{"text":"Buzz","targetRectangle":{"y":665.63244533538818,"x":184.12210083007812,"width":86.6953125,"height":41}},{"text":"11","targetRectangle":{"y":706.63244533538818,"x":184.12210083007812,"width":43.34765625,"height":41}},{"text":"Fizz","targetRectangle":{"y":747.63244533538818,"x":184.12210083007812,"width":86.6953125,"height":41}},{"text":"13","targetRectangle":{"y":788.63244533538818,"x":184.12210083007812,"width":43.34765625,"height":41}},{"text":"14","targetRectangle":{"y":829.63244533538818,"x":184.12210083007812,"width":43.34765625,"height":41}},{"text":"FizzBuzz","targetRectangle":{"y":870.63244533538818,"x":184.12210083007812,"width":173.390625,"height":41}},{"text":"Exercise: fizz_buzz","targetRectangle":{"y":65,"x":581.41199983474598,"width":756.33600035673408,"height":108}}],"baseLayer":{"animations":[],"initialState":{"affineTransform":[1,0,0,1,0,0],"masksToBounds":false,"rotation":0,"scale":1,"position":{"pointX":960,"pointY":540},"width":1920,"sublayerTransform":[1,0,0,0,0,1,0,0,0,0,1,0,0,0,0,1],"contentsRect":{"y":0,"x":0,"width":1,"height":1},"opacity":1,"edgeAntialiasingMask":251658240,"height":1080,"hidden":false,"anchorPoint":{"pointX":0.5,"pointY":0.5}},"objectID":"0","layers":[{"animations":[],"initialState":{"affineTransform":[1,0,0,1,0,0],"masksToBounds":false,"rotation":0,"scale":1,"position":{"pointX":960,"pointY":540},"width":1920,"sublayerTransform":[1,0,0,0,0,1,0,0,0,0,1,-0.00035007912466775983,0,0,0,1],"contentsRect":{"y":0,"x":0,"width":1,"height":1},"opacity":1,"edgeAntialiasingMask":251658240,"height":1080,"hidden":false,"anchorPoint":{"pointX":0.5,"pointY":0.5}},"layers":[{"animations":[],"layers":[],"texturedRectangle":{"isBackgroundTexture":false,"singleTextureOpacity":1,"textureType":0,"textBaseline":0,"textXHeight":0,"isVerticalText":false},"initialState":{"affineTransform":[1,0,0,1,0,0],"masksToBounds":false,"rotation":0,"scale":1,"position":{"pointX":960,"pointY":540},"width":1920,"sublayerTransform":[1,0,0,0,0,1,0,0,0,0,1,0,0,0,0,1],"contentsRect":{"y":0,"x":0,"width":1,"height":1},"opacity":1,"edgeAntialiasingMask":0,"height":1080,"hidden":false,"anchorPoint":{"pointX":0.5,"pointY":0.5}},"texture":"E2B5DC116AB8233B0A2B9A60ACC6231B"}]}]}}]}